__lib_lvgl.cpython-39-darwin.so
lvgl/__init__.py
lvgl/mpy.py
lvgl/__pycache__/__init__.cpython-39.pyc
lvgl-0.1.1b0.dist-info/LICENSE
lvgl-0.1.1b0.dist-info/METADATA
lvgl-0.1.1b0.dist-info/WHEEL
lvgl-0.1.1b0.dist-info/top_level.txt
lvgl-0.1.1b0.dist-info/RECORD
