Metadata-Version: 2.1
Name: lvgl
Version: 0.1.1b0
Summary: README.md
Author: Kevin G. Schlosser, Many other contributors
Maintainer: Kevin G. Schlosser
License: lv_cpython
Project-URL: Homepage, https://github.com/kdschlosser/lv_cpython
Project-URL: Documentation, https://docs.lvgl.io/master/index.html
Project-URL: Repository, https://github.com/kdschlosser/lv_cpython
Project-URL: Issues, https://github.com/kdschlosser/lv_cpython/issues
Project-URL: Forum, https://forum.lvgl.io/
Keywords: LVGL,LV,lvgl,lv,graphics,gui,gui framework
Classifier: Development Status :: 4 - Beta
Classifier: Programming Language :: Python :: 3.6
Classifier: Programming Language :: Python :: 3.7
Classifier: Programming Language :: Python :: 3.8
Classifier: Programming Language :: Python :: 3.9
Classifier: Programming Language :: Python :: 3.10
Classifier: Programming Language :: Python :: 3.11
Classifier: Programming Language :: Python :: 3.12
Classifier: Programming Language :: Python :: Implementation :: CPython
Classifier: Intended Audience :: Developers
Classifier: Topic :: Home Automation
Classifier: Topic :: Multimedia :: Graphics
Classifier: Topic :: Software Development :: Embedded Systems
Classifier: Topic :: Software Development :: User Interfaces
Classifier: Operating System :: Microsoft :: Windows :: Windows 11
Classifier: Operating System :: Microsoft :: Windows :: Windows 10
Classifier: Operating System :: Microsoft :: Windows :: Windows 8
Classifier: Operating System :: Microsoft :: Windows :: Windows 7
Classifier: Operating System :: POSIX :: BSD
Classifier: Operating System :: POSIX :: Linux
Classifier: Operating System :: POSIX :: SunOS/Solaris
Classifier: Operating System :: MacOS :: MacOS X
Requires-Python: >=3.6
License-File: LICENSE
